README.md
setup.py
gauss_binom_dist/Binomialdistribution.py
gauss_binom_dist/Gaussiandistribution.py
gauss_binom_dist/Generaldistribution.py
gauss_binom_dist/__init__.py
gauss_binom_dist.egg-info/PKG-INFO
gauss_binom_dist.egg-info/SOURCES.txt
gauss_binom_dist.egg-info/dependency_links.txt
gauss_binom_dist.egg-info/not-zip-safe
gauss_binom_dist.egg-info/top_level.txt